test/__init__.py
test/readme_parser.py
test/term_info_queries_test.py
test/test_dataset_template_queries.py
test/test_default_caching.py
test/test_examples_code.py
test/test_examples_diff.py
test/test_expression_overlaps.py
test/test_expression_pattern_fragments.py
test/test_images_neurons.py
test/test_images_that_develop_from.py
test/test_lineage_clones_in.py
test/test_nblast_queries.py
test/test_neuron_classes_fasciculating.py
test/test_neuron_inputs.py
test/test_neuron_neuron_connectivity.py
test/test_neuron_region_connectivity.py
test/test_neurons_part_here.py
test/test_new_owlery_queries.py
test/test_publication_transgene_queries.py
test/test_query_performance.py
test/test_similar_morphology.py
test/test_tracts_nerves_innervating.py
test/test_transcriptomics.py
vfbquery/__init__.py
vfbquery/cache_enhancements.py
vfbquery/cached_functions.py
vfbquery/neo4j_client.py
vfbquery/owlery_client.py
vfbquery/solr_cache_integration.py
vfbquery/solr_fetcher.py
vfbquery/solr_result_cache.py
vfbquery/term_info_queries.py
vfbquery/test_utils.py
vfbquery/vfb_queries.py
vfbquery-0.5.3.dist-info/LICENSE
vfbquery-0.5.3.dist-info/METADATA
vfbquery-0.5.3.dist-info/WHEEL
vfbquery-0.5.3.dist-info/top_level.txt
vfbquery-0.5.3.dist-info/RECORD
