Metadata-Version: 2.1
Name: vfbquery
Version: 0.5.3
Summary: Wrapper for querying VirtualFlyBrain knowledge graph.
Home-page: https://github.com/VirtualFlyBrain/VFBquery
Author: VirtualFlyBrain
License: GPL-3.0 License
Project-URL: Bug Reports, https://github.com/VirtualFlyBrain/VFBquery/issues
Project-URL: Source, https://github.com/VirtualFlyBrain/VFBquery
Classifier: Programming Language :: Python :: 3
Classifier: License :: OSI Approved :: GNU General Public License v3 (GPLv3)
Classifier: Operating System :: OS Independent
Requires-Python: >=3.7
License-File: LICENSE
Requires-Dist: pysolr
Requires-Dist: pandas
Requires-Dist: marshmallow
Requires-Dist: vfb-connect
